mcq/__init__.py
mcq/_client.py
mcq-1.2.0.dist-info/LICENSE
mcq-1.2.0.dist-info/METADATA
mcq-1.2.0.dist-info/WHEEL
mcq-1.2.0.dist-info/RECORD
